crudx/__init__.py
crudx/async_crud.py
crudx/errors.py
crudx/helper.py
sqlalchemy_crudx-0.1.0.dist-info/LICENSE
sqlalchemy_crudx-0.1.0.dist-info/METADATA
sqlalchemy_crudx-0.1.0.dist-info/WHEEL
sqlalchemy_crudx-0.1.0.dist-info/RECORD
