Metadata-Version: 2.1
Name: sqlalchemy-crudx
Version: 0.1.0
Summary: Basic async CRUD of SQLAlChemy2
Author: codemaxi
Author-email: codemaxi@163.com
Requires-Python: >=3.10,<4.0
Classifier: Programming Language :: Python :: 3
Classifier: Programming Language :: Python :: 3.10
Classifier: Programming Language :: Python :: 3.11
Classifier: Programming Language :: Python :: 3.12
Requires-Dist: pydantic (>=2.7.4,<3.0.0)
Requires-Dist: sqlalchemy (>=2.0.31,<3.0.0)
